tekore/__init__.py
tekore/_config.py
tekore/_convert.py
tekore/model.py
tekore/_auth/__init__.py
tekore/_auth/refreshing.py
tekore/_auth/scope.py
tekore/_auth/util.py
tekore/_auth/expiring/__init__.py
tekore/_auth/expiring/client.py
tekore/_auth/expiring/decor.py
tekore/_auth/expiring/token.py
tekore/_client/__init__.py
tekore/_client/base.py
tekore/_client/chunked.py
tekore/_client/full.py
tekore/_client/paging.py
tekore/_client/process.py
tekore/_client/short_link.py
tekore/_client/api/__init__.py
tekore/_client/api/album.py
tekore/_client/api/artist.py
tekore/_client/api/audiobook.py
tekore/_client/api/chapter.py
tekore/_client/api/episode.py
tekore/_client/api/follow.py
tekore/_client/api/library.py
tekore/_client/api/markets.py
tekore/_client/api/personalisation.py
tekore/_client/api/search.py
tekore/_client/api/show.py
tekore/_client/api/track.py
tekore/_client/api/user.py
tekore/_client/api/browse/__init__.py
tekore/_client/api/browse/validate.py
tekore/_client/api/player/__init__.py
tekore/_client/api/player/modify.py
tekore/_client/api/player/view.py
tekore/_client/api/playlist/__init__.py
tekore/_client/api/playlist/items.py
tekore/_client/api/playlist/modify.py
tekore/_client/api/playlist/view.py
tekore/_client/decor/__init__.py
tekore/_client/decor/handle.py
tekore/_model/__init__.py
tekore/_model/artist.py
tekore/_model/audio_analysis.py
tekore/_model/audio_features.py
tekore/_model/base.py
tekore/_model/category.py
tekore/_model/context.py
tekore/_model/currently_playing.py
tekore/_model/device.py
tekore/_model/episode.py
tekore/_model/error.py
tekore/_model/local.py
tekore/_model/member.py
tekore/_model/paging.py
tekore/_model/play_history.py
tekore/_model/playlist.py
tekore/_model/recommendations.py
tekore/_model/serialise.py
tekore/_model/track.py
tekore/_model/user.py
tekore/_model/album/__init__.py
tekore/_model/album/base.py
tekore/_model/album/full.py
tekore/_model/audiobook/__init__.py
tekore/_model/audiobook/base.py
tekore-6.1.0.dist-info/licenses/LICENSE
tekore-6.1.0.dist-info/METADATA
tekore-6.1.0.dist-info/WHEEL
tekore-6.1.0.dist-info/top_level.txt
tekore-6.1.0.dist-info/RECORD
