Metadata-Version: 2.4
Name: tekore
Version: 6.1.0
Summary: Client for the Spotify Web API
Author-email: Felix Hildén <felix.hilden@gmail.com>
Maintainer-email: Felix Hildén <felix.hilden@gmail.com>
License-Expression: MIT
Project-URL: Homepage, https://pypi.org/project/tekore
Project-URL: Download, https://pypi.org/project/tekore
Project-URL: Source, https://github.com/felix-hilden/tekore
Project-URL: Issues, https://github.com/felix-hilden/tekore/issues
Project-URL: Documentation, https://tekore.rtfd.org
Keywords: spotify,web,api,client
Classifier: Development Status :: 5 - Production/Stable
Classifier: Intended Audience :: Developers
Classifier: Programming Language :: Python :: 3
Classifier: Programming Language :: Python :: 3 :: Only
Classifier: Programming Language :: Python :: 3.10
Classifier: Programming Language :: Python :: 3.11
Classifier: Programming Language :: Python :: 3.12
Classifier: Programming Language :: Python :: 3.13
Classifier: Programming Language :: Python :: 3.14
Classifier: Topic :: Multimedia :: Sound/Audio
Requires-Python: >=3.10
License-File: LICENSE
Requires-Dist: httpx<0.29,>=0.15
Requires-Dist: pydantic!=2.4.0,!=2.5.0,!=2.5.1,>=1.8
Dynamic: license-file
